{
	"Agilité" : "Rune Age",
	"Chance" : "Rune Cha",
	"% Critique" : "Rune Cri",
	"Dommages" : "Rune Do",
	"Dommages Air" : "Rune Do Air",
	"Dommages Critiques" : "Rune Do Cri",
	"Dommages Eau" : "Rune Do Eau",
	"Dommages Feu" : "Rune Do Feu",
	"Dommages Neutre" : "Rune Do Neutre",
	"% Dommages d'armes" : "Rune Do Per Ar",
	"Dommages distance" : "Rune Do Per Di",
	"Dommages mêlée" : "Rune Do Per Mé",
	"% Dommages aux sorts" : "Rune Do Per So",
	"Dommages Pièges" : "Rune Do Pi",
	"Dommages Poussée" : "Rune Do Pou",
	"Dommages Renvoyés" : "Rune Do Ren",
	"Dommages Terre" : "Rune Do Terre",
	"Force" : "Rune Fo",
	"Fuite" : "Rune Fui",
	"PA" : "Rune Ga Pa",
	"PM" : "Rune Ga Pme",
	"Intelligence" : "Rune Ine",
	"Initiative" : "Rune Ini",
	"Invocation" : "Rune Invo",
	"Puissance Pièges" : "Rune Per Pi",
	"Portée" : "Rune Po",
	"Pod" : "Rune Pod",
	"Prospection" : "Rune Prospe",
	"Puissance" : "Rune Pui",
	"Résistance Air" : "Rune Ré Air",
	"Résistance Critiques" : "Rune Ré Cri",
	"Résistance Eau" : "Rune Ré Eau",
	"Résistance Feu" : "Rune Ré Feu",
	"Résistance Neutre" : "Rune Ré Neutre",
	"Esquive PA" : "Rune Ré Pa",
	"% Résistance Air" : "Rune Ré Per Air",
	"% Résistance distance" : "Rune Ré Per Di",
	"% Résistance Eau" : "Rune Ré Per Eau",
	"% Résistance Feu" : "Rune Ré Per Feu",
	"% Résistance mêlée" : "Rune Ré Per Mé",
	"% Résistance Neutre" : "Rune Ré Per Neutre",
	"% Résistance Terre" : "Rune Ré Per Terre",
	"Esquive PM" : "Rune Ré Pme",
	"Résistance Poussée" : "Rune Ré Pou",
	"Résistance Terre" : "Rune Ré Terre",
	"Retrait PA" : "Rune Ret Pa",
	"Retrait PM" : "Rune Ret Pme",
	"Sagesse" : "Rune Sa",
	"Soin" : "Rune So",
	"Tacle" : "Rune Tac",
	"Vitalité" : "Rune Vi",
	"Arme de chasse" : "Rune de Chasse"
}